{
  "buildCommand" : "prepareForIndexing",
  "configuredTargets" : [
    {
      "guid" : "38622d14f57a3f58c0d32eca170ecd8088a783a885d8b0b3beb2e9f90bde3f49"
    }
  ],
  "continueBuildingAfterErrors" : true,
  "enableIndexBuildArena" : false,
  "hideShellScriptEnvironment" : false,
  "parameters" : {
    "action" : "build",
    "activeArchitecture" : "arm64",
    "activeRunDestination" : {
      "disableOnlyActiveArch" : false,
      "platform" : "iphonesimulator",
      "sdk" : "iphonesimulator14.5",
      "sdkVariant" : "iphonesimulator",
      "supportedArchitectures" : [
        "arm64",
        "x86_64"
      ],
      "targetArchitecture" : "arm64"
    },
    "arenaInfo" : {
      "buildIntermediatesPath" : "",
      "buildProductsPath" : "",
      "derivedDataPath" : "/Users/karl/Library/Developer/Xcode/DerivedData",
      "indexDataStoreFolderPath" : "/Users/karl/Library/Developer/Xcode/DerivedData/Runner-bqoymyzhksebemfpppxvijraazzs/Index/DataStore",
      "indexEnableDataStore" : true,
      "indexPCHPath" : "/Users/karl/Library/Developer/Xcode/DerivedData/Runner-bqoymyzhksebemfpppxvijraazzs/Index/PrecompiledHeaders",
      "pchPath" : ""
    },
    "configurationName" : "Debug",
    "overrides" : {
      "synthesized" : {
        "table" : {
          "ASSETCATALOG_FILTER_FOR_DEVICE_MODEL" : "iPod9,1",
          "ASSETCATALOG_FILTER_FOR_DEVICE_OS_VERSION" : "14.5",
          "BUILD_ACTIVE_RESOURCES_ONLY" : "YES",
          "ENABLE_PREVIEWS" : "NO",
          "TARGET_DEVICE_IDENTIFIER" : "3271D1FC-F2C8-465D-B6BD-47F574515882",
          "TARGET_DEVICE_MODEL" : "iPod9,1",
          "TARGET_DEVICE_OS_VERSION" : "14.5",
          "TARGET_DEVICE_PLATFORM_NAME" : "iphonesimulator"
        }
      }
    }
  },
  "qos" : "default",
  "schemeCommand" : "launch",
  "shouldCollectMetrics" : false,
  "showNonLoggedProgress" : true,
  "useDryRun" : true,
  "useImplicitDependencies" : true,
  "useLegacyBuildLocations" : false,
  "useParallelTargets" : true
}